hostlist.py
lrms_simple.py
ui_loader.py
ui_loader_utils.py
whisper-gui.py
whisper.py
whisper_slurm_gui-0.1.0.dist-info/METADATA
whisper_slurm_gui-0.1.0.dist-info/WHEEL
whisper_slurm_gui-0.1.0.dist-info/entry_points.txt
whisper_slurm_gui-0.1.0.dist-info/licenses/LICENSE
whisper_slurm_gui-0.1.0.dist-info/RECORD
