Metadata-Version: 2.1
Name: whisper-slurm-gui
Version: 0.1.0
Summary: A Whisper ASR job submission GUI with Slurm integration.
Author-Email: Jonas Lindemann <jonas.lindemann@lunarc.lu.se>
Requires-Python: >=3.8
Requires-Dist: PyQt5
